[
    {
        "Label": "DAILYS",
        "FundData": [
            {
                "Name": "Alfred Berg Aktiv R (NOK)",
                "PPMCode": "147348",
                "URL": "https://www.avanza.se/fonder/om-fonden.html/1340461",
                "Current": 7.926648161557445,
                "Yesterday": 5.6940258693275965,
                "LastWeek": 4.800167930544512,
                "TrendDay": "\u25b2",
                "TrendWeek": "\u25b2",
                "TrendAwesome": "\ud83d\udcaa",
                "Label": "DAILYS",
                "LastUpdated": "2025-08-21 22:09:38 (UTC)",
                "history": false
            },
            {
                "Name": "BGF World Gold A2",
                "PPMCode": "338590",
                "URL": "https://www.avanza.se/fonder/om-fonden.html/492",
                "Current": 16.478322044862754,
                "Yesterday": 14.562972350871616,
                "LastWeek": 14.846528993320204,
                "TrendDay": "\u25b2",
                "TrendWeek": "\u25b2",
                "TrendAwesome": "\ud83d\udcaa",
                "Label": "DAILYS",
                "LastUpdated": "2025-08-21 22:09:40 (UTC)",
                "history": false
            },
            {
                "Name": "BGF World Gold A2",
                "PPMCode": "338590",
                "URL": "https://www.avanza.se/fonder/om-fonden.html/492",
                "Current": 16.478322044862754,
                "Yesterday": 14.562972350871616,
                "LastWeek": 14.846528993320204,
                "TrendDay": "\u25b2",
                "TrendWeek": "\u25b2",
                "TrendAwesome": "\ud83d\udcaa",
                "Label": "DAILYS",
                "LastUpdated": "2025-08-21 20:10:56 (UTC)",
                "history": true
            },
            {
                "Name": "BGF World Mining A2",
                "PPMCode": "481911",
                "URL": "https://www.avanza.se/fonder/om-fonden.html/2821",
                "Current": 12.485143175844613,
                "Yesterday": 11.530919818925147,
                "LastWeek": 13.338985635857222,
                "TrendDay": "\u25b2",
                "TrendWeek": "\u25bc",
                "TrendAwesome": "",
                "Label": "DAILYS",
                "LastUpdated": "2025-08-21 18:14:26 (UTC)",
                "history": true
            },
            {
                "Name": "Swedbank Robur Fastighet A",
                "PPMCode": "968420",
                "URL": "https://www.avanza.se/fonder/om-fonden.html/347",
                "Current": 2.06215509729887,
                "Yesterday": 0.6970665117630032,
                "LastWeek": 1.3941330235259857,
                "TrendDay": "\u25b2",
                "TrendWeek": "\u25b2",
                "TrendAwesome": "\ud83d\udcaa",
                "Label": "DAILYS",
                "LastUpdated": "2025-08-21 16:16:59 (UTC)",
                "history": true
            },
            {
                "Name": "Indecap Guide Sverige C",
                "PPMCode": "106849",
                "URL": "https://www.avanza.se/fonder/om-fonden.html/483296",
                "Current": 1.6081022215768865,
                "Yesterday": -0.021780165529258846,
                "LastWeek": -0.11616088282270698,
                "TrendDay": "\u25b2",
                "TrendWeek": "\u25b2",
                "TrendAwesome": "\ud83d\udcaa",
                "Label": "DAILYS",
                "LastUpdated": "2025-08-21 12:19:06 (UTC)",
                "history": true
            },
            {
                "Name": "Evli Sverige Sm\u00e5bolag B",
                "PPMCode": "420463",
                "URL": "https://www.avanza.se/fonder/om-fonden.html/137448",
                "Current": 2.614593076497714,
                "Yesterday": 0.8189459867729985,
                "LastWeek": 1.698820282052301,
                "TrendDay": "\u25b2",
                "TrendWeek": "\u25b2",
                "TrendAwesome": "\ud83d\udcaa",
                "Label": "DAILYS",
                "LastUpdated": "2025-08-21 10:10:35 (UTC)",
                "history": true
            },
            {
                "Name": "PriorNilsson Sverige Aktiv A",
                "PPMCode": "328021",
                "URL": "https://www.avanza.se/fonder/om-fonden.html/377801",
                "Current": 1.7592183123802296,
                "Yesterday": 0.2190073072630519,
                "LastWeek": -0.3600985532882569,
                "TrendDay": "\u25b2",
                "TrendWeek": "\u25b2",
                "TrendAwesome": "\ud83d\udcaa",
                "Label": "DAILYS",
                "LastUpdated": "2025-08-21 10:10:42 (UTC)",
                "history": true
            },
            {
                "Name": "L\u00e4nsf\u00f6rs\u00e4kringar Sm\u00e5bolag Sverige Vis A",
                "PPMCode": "515676",
                "URL": "https://www.avanza.se/fonder/om-fonden.html/2011",
                "Current": -2.092141300185067,
                "Yesterday": -3.6997599385197337,
                "LastWeek": -2.5352834379799383,
                "TrendDay": "\u25b2",
                "TrendWeek": "\u25b2",
                "TrendAwesome": "\ud83d\udcaa",
                "Label": "DAILYS",
                "LastUpdated": "2025-08-21 08:13:59 (UTC)",
                "history": true
            },
            {
                "Name": "\u00d6hman Sverige A",
                "PPMCode": "904904",
                "URL": "https://www.avanza.se/fonder/om-fonden.html/430255",
                "Current": 3.4715047319915717,
                "Yesterday": 1.7274868785386648,
                "LastWeek": 1.615902797867503,
                "TrendDay": "\u25b2",
                "TrendWeek": "\u25b2",
                "TrendAwesome": "\ud83d\udcaa",
                "Label": "DAILYS",
                "LastUpdated": "2025-08-21 06:20:21 (UTC)",
                "history": true
            },
            {
                "Name": "Storebrand Sverige A SEK",
                "PPMCode": "212332",
                "URL": "https://www.avanza.se/fonder/om-fonden.html/1950",
                "Current": 1.9666646416723004,
                "Yesterday": 0.31163922305411246,
                "LastWeek": 0.03761673968992942,
                "TrendDay": "\u25b2",
                "TrendWeek": "\u25b2",
                "TrendAwesome": "\ud83d\udcaa",
                "Label": "DAILYS",
                "LastUpdated": "2025-08-21 06:20:26 (UTC)",
                "history": true
            },
            {
                "Name": "\u00d6hman Marknad Sverige Bred A",
                "PPMCode": "577833",
                "URL": "https://www.avanza.se/fonder/om-fonden.html/24328",
                "Current": 2.2356389727435855,
                "Yesterday": 0.586253664085402,
                "LastWeek": 0.41344008400052207,
                "TrendDay": "\u25b2",
                "TrendWeek": "\u25b2",
                "TrendAwesome": "\ud83d\udcaa",
                "Label": "DAILYS",
                "LastUpdated": "2025-08-21 06:20:30 (UTC)",
                "history": true
            },
            {
                "Name": "Spiltan Aktiefond Sm\u00e5land",
                "PPMCode": "272898",
                "URL": "https://www.avanza.se/fonder/om-fonden.html/132510",
                "Current": 1.5575916230366587,
                "Yesterday": -0.7569808027923147,
                "LastWeek": 0.4264834205933772,
                "TrendDay": "\u25b2",
                "TrendWeek": "\u25b2",
                "TrendAwesome": "\ud83d\udcaa",
                "Label": "DAILYS",
                "LastUpdated": "2025-08-20 20:11:08 (UTC)",
                "history": true
            },
            {
                "Name": "Spiltan Aktiefond Stabil",
                "PPMCode": "339184",
                "URL": "https://www.avanza.se/fonder/om-fonden.html/2016",
                "Current": 2.18905783138171,
                "Yesterday": 0.3307770921261017,
                "LastWeek": 0.35262086236084206,
                "TrendDay": "\u25b2",
                "TrendWeek": "\u25b2",
                "TrendAwesome": "\ud83d\udcaa",
                "Label": "DAILYS",
                "LastUpdated": "2025-08-20 20:11:14 (UTC)",
                "history": true
            },
            {
                "Name": "Spiltan Sm\u00e5bolagsfond",
                "PPMCode": "152181",
                "URL": "https://www.avanza.se/fonder/om-fonden.html/1996",
                "Current": 1.4111975037086255,
                "Yesterday": -0.34336794720958347,
                "LastWeek": 0.8178167681211292,
                "TrendDay": "\u25b2",
                "TrendWeek": "\u25b2",
                "TrendAwesome": "\ud83d\udcaa",
                "Label": "DAILYS",
                "LastUpdated": "2025-08-20 20:11:18 (UTC)",
                "history": true
            },
            {
                "Name": "Handelsbanken Svenska Sm\u00e5bolag (A1 SEK)",
                "PPMCode": "952010",
                "URL": "https://www.avanza.se/fonder/om-fonden.html/2006",
                "Current": -1.3646439456913184,
                "Yesterday": -3.0108552149039114,
                "LastWeek": -1.3687187260606528,
                "TrendDay": "\u25b2",
                "TrendWeek": "\u25b2",
                "TrendAwesome": "\ud83d\udcaa",
                "Label": "DAILYS",
                "LastUpdated": "2025-08-20 16:12:21 (UTC)",
                "history": true
            },
            {
                "Name": "Lannebo Sm\u00e5bolag",
                "PPMCode": "842690",
                "URL": "https://www.avanza.se/fonder/om-fonden.html/2014",
                "Current": 0.9141536198381891,
                "Yesterday": -0.8878848376589249,
                "LastWeek": 0.5516444257644126,
                "TrendDay": "\u25b2",
                "TrendWeek": "\u25b2",
                "TrendAwesome": "\ud83d\udcaa",
                "Label": "DAILYS",
                "LastUpdated": "2025-08-20 14:10:24 (UTC)",
                "history": true
            },
            {
                "Name": "D&G Aktiefond",
                "PPMCode": "291906",
                "URL": "https://www.avanza.se/fonder/om-fonden.html/1919",
                "Current": 1.6015252853950728,
                "Yesterday": -0.0761473387912598,
                "LastWeek": 0.03345625079967173,
                "TrendDay": "\u25b2",
                "TrendWeek": "\u25b2",
                "TrendAwesome": "\ud83d\udcaa",
                "Label": "DAILYS",
                "LastUpdated": "2025-08-20 10:11:00 (UTC)",
                "history": true
            },
            {
                "Name": "Nordea Indienfond",
                "PPMCode": "469692",
                "URL": "https://www.avanza.se/fonder/om-fonden.html/43947",
                "Current": -4.802419791951028,
                "Yesterday": -6.459393089560443,
                "LastWeek": -4.731165710908402,
                "TrendDay": "\u25b2",
                "TrendWeek": "\u25bc",
                "TrendAwesome": "",
                "Label": "DAILYS",
                "LastUpdated": "2025-08-20 00:46:53 (UTC)",
                "history": true
            },
            {
                "Name": "BGF Sustainable Energy A2",
                "PPMCode": "553578",
                "URL": "https://www.avanza.se/fonder/om-fonden.html/547",
                "Current": 10.561071190939783,
                "Yesterday": 6.206158276820969,
                "LastWeek": 6.083688390800586,
                "TrendDay": "\u25b2",
                "TrendWeek": "\u25b2",
                "TrendAwesome": "\ud83d\udcaa",
                "Label": "DAILYS",
                "LastUpdated": "2025-08-19 18:13:52 (UTC)",
                "history": true
            },
            {
                "Name": "BGF World Healthscience A2",
                "PPMCode": "374421",
                "URL": "https://www.avanza.se/fonder/om-fonden.html/475",
                "Current": 1.4650357392965445,
                "Yesterday": -0.964797662927124,
                "LastWeek": -2.0349341131699434,
                "TrendDay": "\u25b2",
                "TrendWeek": "\u25b2",
                "TrendAwesome": "\ud83d\udcaa",
                "Label": "DAILYS",
                "LastUpdated": "2025-08-19 18:13:55 (UTC)",
                "history": true
            },
            {
                "Name": "Pictet-Biotech R USD",
                "PPMCode": "260919",
                "URL": "https://www.avanza.se/fonder/om-fonden.html/459",
                "Current": 20.939806781722154,
                "Yesterday": 19.1199155322753,
                "LastWeek": 15.41957275795404,
                "TrendDay": "\u25b2",
                "TrendWeek": "\u25b2",
                "TrendAwesome": "\ud83d\udcaa",
                "Label": "DAILYS",
                "LastUpdated": "2025-08-19 18:14:02 (UTC)",
                "history": true
            },
            {
                "Name": "Pictet-Indian Equities R USD",
                "PPMCode": "874271",
                "URL": "https://www.avanza.se/fonder/om-fonden.html/121",
                "Current": -3.271756014915925,
                "Yesterday": -4.69023117541766,
                "LastWeek": -5.12965171687977,
                "TrendDay": "\u25b2",
                "TrendWeek": "\u25b2",
                "TrendAwesome": "\ud83d\udcaa",
                "Label": "DAILYS",
                "LastUpdated": "2025-08-19 18:14:04 (UTC)",
                "history": true
            },
            {
                "Name": "Allianz China A Shares AT USD",
                "PPMCode": "933359",
                "URL": "https://www.avanza.se/fonder/om-fonden.html/1011686",
                "Current": 12.082644174388632,
                "Yesterday": 9.431962618991982,
                "LastWeek": 6.802969954657796,
                "TrendDay": "\u25b2",
                "TrendWeek": "\u25b2",
                "TrendAwesome": "\ud83d\udcaa",
                "Label": "DAILYS",
                "LastUpdated": "2025-08-19 14:09:54 (UTC)",
                "history": true
            },
            {
                "Name": "L\u00e4nsf\u00f6rs\u00e4kringar Japan Index",
                "PPMCode": "470104",
                "URL": "https://www.avanza.se/fonder/om-fonden.html/1268",
                "Current": 10.37417571808006,
                "Yesterday": 7.969041118830453,
                "LastWeek": 4.045410763952761,
                "TrendDay": "\u25b2",
                "TrendWeek": "\u25b2",
                "TrendAwesome": "\ud83d\udcaa",
                "Label": "DAILYS",
                "LastUpdated": "2025-08-19 06:15:31 (UTC)",
                "history": true
            },
            {
                "Name": "Storebrand Japan A SEK",
                "PPMCode": "176503",
                "URL": "https://www.avanza.se/fonder/om-fonden.html/1288",
                "Current": 10.294064645566655,
                "Yesterday": 8.103897235053493,
                "LastWeek": 4.1604095460634145,
                "TrendDay": "\u25b2",
                "TrendWeek": "\u25b2",
                "TrendAwesome": "\ud83d\udcaa",
                "Label": "DAILYS",
                "LastUpdated": "2025-08-19 06:15:34 (UTC)",
                "history": true
            },
            {
                "Name": "Pictet-Japanese Equity Opps R JPY",
                "PPMCode": "910109",
                "URL": "https://www.avanza.se/fonder/om-fonden.html/1324",
                "Current": 7.624245423591514,
                "Yesterday": 5.2299009718157015,
                "LastWeek": 2.4585765242408746,
                "TrendDay": "\u25b2",
                "TrendWeek": "\u25b2",
                "TrendAwesome": "\ud83d\udcaa",
                "Label": "DAILYS",
                "LastUpdated": "2025-08-18 18:14:59 (UTC)",
                "history": true
            },
            {
                "Name": "Skandia Japan Exponering",
                "PPMCode": "582791",
                "URL": "https://www.avanza.se/fonder/om-fonden.html/1263",
                "Current": 9.603113833588573,
                "Yesterday": 7.803726391015818,
                "LastWeek": 3.6242981112812704,
                "TrendDay": "\u25b2",
                "TrendWeek": "\u25b2",
                "TrendAwesome": "\ud83d\udcaa",
                "Label": "DAILYS",
                "LastUpdated": "2025-08-18 16:12:54 (UTC)",
                "history": true
            },
            {
                "Name": "Allianz Global Water AT EUR",
                "PPMCode": "878694",
                "URL": "https://www.avanza.se/fonder/om-fonden.html/909774",
                "Current": 6.519006580853929,
                "Yesterday": 4.923088189160016,
                "LastWeek": 3.513659548139943,
                "TrendDay": "\u25b2",
                "TrendWeek": "\u25b2",
                "TrendAwesome": "\ud83d\udcaa",
                "Label": "DAILYS",
                "LastUpdated": "2025-08-18 14:12:05 (UTC)",
                "history": true
            },
            {
                "Name": "DNB Health Care S",
                "PPMCode": "255001",
                "URL": "https://www.avanza.se/fonder/om-fonden.html/1506920",
                "Current": -0.42997297132179624,
                "Yesterday": -2.0244894290411155,
                "LastWeek": 0.0454972216428773,
                "TrendDay": "\u25b2",
                "TrendWeek": "\u25bc",
                "TrendAwesome": "",
                "Label": "DAILYS",
                "LastUpdated": "2025-08-15 10:11:11 (UTC)",
                "history": true
            },
            {
                "Name": "L\u00e4nsf\u00f6rs\u00e4kringar Asienfond A",
                "PPMCode": "385401",
                "URL": "https://www.avanza.se/fonder/om-fonden.html/146",
                "Current": 6.41119021727981,
                "Yesterday": 4.72250148751514,
                "LastWeek": 4.955477133301875,
                "TrendDay": "\u25b2",
                "TrendWeek": "\u25b2",
                "TrendAwesome": "\ud83d\udcaa",
                "Label": "DAILYS",
                "LastUpdated": "2025-08-15 06:15:54 (UTC)",
                "history": true
            }
        ]
    },
    {
        "Label": "WEEKLYS",
        "FundData": [
            {
                "Name": "Handelsbanken H\u00e5llbar Energi (A1 SEK)",
                "PPMCode": "687509",
                "URL": "https://www.avanza.se/fonder/om-fonden.html/512559",
                "Current": 14.294443383616553,
                "Yesterday": 14.794729807141474,
                "LastWeek": 8.161160970021006,
                "TrendDay": "\u25bc",
                "TrendWeek": "\u25b2",
                "TrendAwesome": "",
                "Label": "WEEKLYS",
                "LastUpdated": "2025-08-21 22:09:53 (UTC)",
                "history": false
            },
            {
                "Name": "Nordea Indienfond",
                "PPMCode": "469692",
                "URL": "https://www.avanza.se/fonder/om-fonden.html/43947",
                "Current": -0.5264470346219181,
                "Yesterday": -1.4249299331686707,
                "LastWeek": -3.6616429777569555,
                "TrendDay": "\u25b2",
                "TrendWeek": "\u25b2",
                "TrendAwesome": "\ud83d\udcaa",
                "Label": "WEEKLYS",
                "LastUpdated": "2025-08-21 22:09:57 (UTC)",
                "history": false
            },
            {
                "Name": "DNB Health Care S",
                "PPMCode": "255001",
                "URL": "https://www.avanza.se/fonder/om-fonden.html/1506920",
                "Current": 1.6131128581459768,
                "Yesterday": 0.5257672343765147,
                "LastWeek": -4.31307568393662,
                "TrendDay": "\u25b2",
                "TrendWeek": "\u25b2",
                "TrendAwesome": "\ud83d\udcaa",
                "Label": "WEEKLYS",
                "LastUpdated": "2025-08-21 22:09:59 (UTC)",
                "history": false
            },
            {
                "Name": "BGF Sustainable Energy A2",
                "PPMCode": "553578",
                "URL": "https://www.avanza.se/fonder/om-fonden.html/547",
                "Current": 13.335292832200446,
                "Yesterday": 13.56047078259827,
                "LastWeek": 8.647331865245862,
                "TrendDay": "\u25bc",
                "TrendWeek": "\u25b2",
                "TrendAwesome": "",
                "Label": "WEEKLYS",
                "LastUpdated": "2025-08-21 22:10:03 (UTC)",
                "history": false
            },
            {
                "Name": "SEB L\u00e4kemedelsfond",
                "PPMCode": "229922",
                "URL": "https://www.avanza.se/fonder/om-fonden.html/473",
                "Current": 4.690577137199298,
                "Yesterday": 4.456646707021189,
                "LastWeek": -0.9538558625867197,
                "TrendDay": "\u25b2",
                "TrendWeek": "\u25b2",
                "TrendAwesome": "\ud83d\udcaa",
                "Label": "WEEKLYS",
                "LastUpdated": "2025-08-21 22:10:05 (UTC)",
                "history": false
            },
            {
                "Name": "BGF World Healthscience A2",
                "PPMCode": "374421",
                "URL": "https://www.avanza.se/fonder/om-fonden.html/475",
                "Current": 3.7384839892240582,
                "Yesterday": 3.7111932237193446,
                "LastWeek": -0.4166505298732085,
                "TrendDay": "\u25b2",
                "TrendWeek": "\u25b2",
                "TrendAwesome": "\ud83d\udcaa",
                "Label": "WEEKLYS",
                "LastUpdated": "2025-08-21 22:10:07 (UTC)",
                "history": false
            },
            {
                "Name": "Allianz China A Shares AT USD",
                "PPMCode": "933359",
                "URL": "https://www.avanza.se/fonder/om-fonden.html/1011686",
                "Current": 14.697885584834902,
                "Yesterday": 14.521775149348557,
                "LastWeek": 9.121558488910654,
                "TrendDay": "\u25b2",
                "TrendWeek": "\u25b2",
                "TrendAwesome": "\ud83d\udcaa",
                "Label": "WEEKLYS",
                "LastUpdated": "2025-08-21 22:10:09 (UTC)",
                "history": false
            },
            {
                "Name": "Handelsbanken H\u00e4lsov\u00e5rd Tema (A1 SEK)",
                "PPMCode": "644005",
                "URL": "https://www.avanza.se/fonder/om-fonden.html/464",
                "Current": 4.799560105784081,
                "Yesterday": 4.67649446204602,
                "LastWeek": -0.539394098085937,
                "TrendDay": "\u25b2",
                "TrendWeek": "\u25b2",
                "TrendAwesome": "\ud83d\udcaa",
                "Label": "WEEKLYS",
                "LastUpdated": "2025-08-21 22:10:10 (UTC)",
                "history": false
            },
            {
                "Name": "Handelsbanken H\u00e5llbar Energi (A1 SEK)",
                "PPMCode": "687509",
                "URL": "https://www.avanza.se/fonder/om-fonden.html/512559",
                "Current": 14.294443383616553,
                "Yesterday": 14.794729807141474,
                "LastWeek": 8.161160970021006,
                "TrendDay": "\u25bc",
                "TrendWeek": "\u25b2",
                "TrendAwesome": "",
                "Label": "WEEKLYS",
                "LastUpdated": "2025-08-21 20:11:06 (UTC)",
                "history": true
            },
            {
                "Name": "Nordea Indienfond",
                "PPMCode": "469692",
                "URL": "https://www.avanza.se/fonder/om-fonden.html/43947",
                "Current": -0.5264470346219181,
                "Yesterday": -1.4249299331686707,
                "LastWeek": -3.6616429777569555,
                "TrendDay": "\u25b2",
                "TrendWeek": "\u25b2",
                "TrendAwesome": "\ud83d\udcaa",
                "Label": "WEEKLYS",
                "LastUpdated": "2025-08-21 20:11:08 (UTC)",
                "history": true
            },
            {
                "Name": "DNB Health Care S",
                "PPMCode": "255001",
                "URL": "https://www.avanza.se/fonder/om-fonden.html/1506920",
                "Current": 1.6131128581459768,
                "Yesterday": 0.5257672343765147,
                "LastWeek": -4.31307568393662,
                "TrendDay": "\u25b2",
                "TrendWeek": "\u25b2",
                "TrendAwesome": "\ud83d\udcaa",
                "Label": "WEEKLYS",
                "LastUpdated": "2025-08-21 20:11:10 (UTC)",
                "history": true
            },
            {
                "Name": "SEB L\u00e4kemedelsfond",
                "PPMCode": "229922",
                "URL": "https://www.avanza.se/fonder/om-fonden.html/473",
                "Current": 4.690577137199298,
                "Yesterday": 4.456646707021189,
                "LastWeek": -0.9538558625867197,
                "TrendDay": "\u25b2",
                "TrendWeek": "\u25b2",
                "TrendAwesome": "\ud83d\udcaa",
                "Label": "WEEKLYS",
                "LastUpdated": "2025-08-21 20:11:12 (UTC)",
                "history": true
            },
            {
                "Name": "BGF World Healthscience A2",
                "PPMCode": "374421",
                "URL": "https://www.avanza.se/fonder/om-fonden.html/475",
                "Current": 3.7384839892240582,
                "Yesterday": 3.7111932237193446,
                "LastWeek": -0.4166505298732085,
                "TrendDay": "\u25b2",
                "TrendWeek": "\u25b2",
                "TrendAwesome": "\ud83d\udcaa",
                "Label": "WEEKLYS",
                "LastUpdated": "2025-08-21 20:11:13 (UTC)",
                "history": true
            },
            {
                "Name": "Allianz China A Shares AT USD",
                "PPMCode": "933359",
                "URL": "https://www.avanza.se/fonder/om-fonden.html/1011686",
                "Current": 14.697885584834902,
                "Yesterday": 14.521775149348557,
                "LastWeek": 9.121558488910654,
                "TrendDay": "\u25b2",
                "TrendWeek": "\u25b2",
                "TrendAwesome": "\ud83d\udcaa",
                "Label": "WEEKLYS",
                "LastUpdated": "2025-08-21 20:11:15 (UTC)",
                "history": true
            },
            {
                "Name": "Handelsbanken H\u00e4lsov\u00e5rd Tema (A1 SEK)",
                "PPMCode": "644005",
                "URL": "https://www.avanza.se/fonder/om-fonden.html/464",
                "Current": 4.799560105784081,
                "Yesterday": 4.67649446204602,
                "LastWeek": -0.539394098085937,
                "TrendDay": "\u25b2",
                "TrendWeek": "\u25b2",
                "TrendAwesome": "\ud83d\udcaa",
                "Label": "WEEKLYS",
                "LastUpdated": "2025-08-21 20:11:15 (UTC)",
                "history": true
            },
            {
                "Name": "BGF Sustainable Energy A2",
                "PPMCode": "553578",
                "URL": "https://www.avanza.se/fonder/om-fonden.html/547",
                "Current": 13.335292832200446,
                "Yesterday": 13.56047078259827,
                "LastWeek": 8.647331865245862,
                "TrendDay": "\u25bc",
                "TrendWeek": "\u25b2",
                "TrendAwesome": "",
                "Label": "WEEKLYS",
                "LastUpdated": "2025-08-21 20:11:17 (UTC)",
                "history": true
            },
            {
                "Name": "Swedbank Robur Healthcare A",
                "PPMCode": "928341",
                "URL": "https://www.avanza.se/fonder/om-fonden.html/453",
                "Current": 0.9711595055915404,
                "Yesterday": -0.3237198351971732,
                "LastWeek": -3.472630959387875,
                "TrendDay": "\u25b2",
                "TrendWeek": "\u25b2",
                "TrendAwesome": "\ud83d\udcaa",
                "Label": "WEEKLYS",
                "LastUpdated": "2025-08-21 16:17:08 (UTC)",
                "history": true
            },
            {
                "Name": "Allianz China Equity A USD",
                "PPMCode": "753731",
                "URL": "https://www.avanza.se/fonder/om-fonden.html/286894",
                "Current": 13.074654526762671,
                "Yesterday": 12.73208196577258,
                "LastWeek": 9.04933463381897,
                "TrendDay": "\u25b2",
                "TrendWeek": "\u25b2",
                "TrendAwesome": "\ud83d\udcaa",
                "Label": "WEEKLYS",
                "LastUpdated": "2025-08-20 14:10:48 (UTC)",
                "history": true
            },
            {
                "Name": "Pictet-Biotech R USD",
                "PPMCode": "260919",
                "URL": "https://www.avanza.se/fonder/om-fonden.html/459",
                "Current": 20.939806781722154,
                "Yesterday": 19.1199155322753,
                "LastWeek": 15.41957275795404,
                "TrendDay": "\u25b2",
                "TrendWeek": "\u25b2",
                "TrendAwesome": "\ud83d\udcaa",
                "Label": "WEEKLYS",
                "LastUpdated": "2025-08-19 18:14:10 (UTC)",
                "history": true
            },
            {
                "Name": "L\u00e4nsf\u00f6rs\u00e4kringar Japan Index",
                "PPMCode": "470104",
                "URL": "https://www.avanza.se/fonder/om-fonden.html/1268",
                "Current": 10.37417571808006,
                "Yesterday": 7.969041118830453,
                "LastWeek": 4.045410763952761,
                "TrendDay": "\u25b2",
                "TrendWeek": "\u25b2",
                "TrendAwesome": "\ud83d\udcaa",
                "Label": "WEEKLYS",
                "LastUpdated": "2025-08-19 06:15:44 (UTC)",
                "history": true
            },
            {
                "Name": "Storebrand Japan A SEK",
                "PPMCode": "176503",
                "URL": "https://www.avanza.se/fonder/om-fonden.html/1288",
                "Current": 10.294064645566655,
                "Yesterday": 8.103897235053493,
                "LastWeek": 4.1604095460634145,
                "TrendDay": "\u25b2",
                "TrendWeek": "\u25b2",
                "TrendAwesome": "\ud83d\udcaa",
                "Label": "WEEKLYS",
                "LastUpdated": "2025-08-18 16:13:07 (UTC)",
                "history": true
            },
            {
                "Name": "Skandia Japan Exponering",
                "PPMCode": "582791",
                "URL": "https://www.avanza.se/fonder/om-fonden.html/1263",
                "Current": 9.603113833588573,
                "Yesterday": 7.803726391015818,
                "LastWeek": 3.6242981112812704,
                "TrendDay": "\u25b2",
                "TrendWeek": "\u25b2",
                "TrendAwesome": "\ud83d\udcaa",
                "Label": "WEEKLYS",
                "LastUpdated": "2025-08-18 08:16:37 (UTC)",
                "history": true
            },
            {
                "Name": "Allianz Global Metals and Mining A EUR",
                "PPMCode": "502922",
                "URL": "https://www.avanza.se/fonder/om-fonden.html/334858",
                "Current": 12.367892423542802,
                "Yesterday": 12.152952555756457,
                "LastWeek": 6.880399902311726,
                "TrendDay": "\u25b2",
                "TrendWeek": "\u25b2",
                "TrendAwesome": "\ud83d\udcaa",
                "Label": "WEEKLYS",
                "LastUpdated": "2025-08-15 16:12:29 (UTC)",
                "history": true
            }
        ]
    }
]