[
    {
        "Label": "DAILYS",
        "FundData": [
            {
                "Name": "BGF Asian Dragon A2",
                "PPMCode": "608463",
                "URL": "https://www.avanza.se/fonder/om-fonden.html/58",
                "Current": 18.801679212393992,
                "Yesterday": 22.864573320645995,
                "LastWeek": 22.677973682205995,
                "TrendDay": "\u25bc",
                "TrendWeek": "\u25bc",
                "TrendAwesome": "",
                "Label": "DAILYS",
                "LastUpdated": "2026-06-09 21:28:03 (UTC)",
                "history": false
            },
            {
                "Name": "BGF Emerging Markets A2",
                "PPMCode": "231100",
                "URL": "https://www.avanza.se/fonder/om-fonden.html/2145",
                "Current": 20.92064817667,
                "Yesterday": 24.60025500395899,
                "LastWeek": 25.346439225734997,
                "TrendDay": "\u25bc",
                "TrendWeek": "\u25bc",
                "TrendAwesome": "",
                "Label": "DAILYS",
                "LastUpdated": "2026-06-09 21:28:09 (UTC)",
                "history": false
            }
        ]
    },
    {
        "Label": "WEEKLYS",
        "FundData": [
            {
                "Name": "BGF World Healthscience A2",
                "PPMCode": "374421",
                "URL": "https://www.avanza.se/fonder/om-fonden.html/475",
                "Current": 1.6102123397959986,
                "Yesterday": 1.9198599494120026,
                "LastWeek": -0.8746286191810032,
                "TrendDay": "\u25bc",
                "TrendWeek": "\u25b2",
                "TrendAwesome": "",
                "Label": "WEEKLYS",
                "LastUpdated": "2026-06-09 21:28:12 (UTC)",
                "history": false
            },
            {
                "Name": "Handelsbanken H\u00e4lsov\u00e5rd Tema (A1 SEK)",
                "PPMCode": "644005",
                "URL": "https://www.avanza.se/fonder/om-fonden.html/464",
                "Current": -1.2340364471135035,
                "Yesterday": -0.9781412923806965,
                "LastWeek": -2.841153680576008,
                "TrendDay": "\u25bc",
                "TrendWeek": "\u25b2",
                "TrendAwesome": "",
                "Label": "WEEKLYS",
                "LastUpdated": "2026-06-09 21:28:16 (UTC)",
                "history": false
            },
            {
                "Name": "SEB L\u00e4kemedelsfond",
                "PPMCode": "229922",
                "URL": "https://www.avanza.se/fonder/om-fonden.html/473",
                "Current": 0.312905417014008,
                "Yesterday": 0.6969549667089996,
                "LastWeek": -0.6261327528723996,
                "TrendDay": "\u25bc",
                "TrendWeek": "\u25b2",
                "TrendAwesome": "",
                "Label": "WEEKLYS",
                "LastUpdated": "2026-06-09 21:28:17 (UTC)",
                "history": false
            },
            {
                "Name": "Pictet-Biotech R USD",
                "PPMCode": "260919",
                "URL": "https://www.avanza.se/fonder/om-fonden.html/459",
                "Current": 2.293784812092999,
                "Yesterday": 4.777153384337998,
                "LastWeek": 5.105413493015003,
                "TrendDay": "\u25bc",
                "TrendWeek": "\u25bc",
                "TrendAwesome": "",
                "Label": "WEEKLYS",
                "LastUpdated": "2026-06-09 21:28:19 (UTC)",
                "history": false
            },
            {
                "Name": "Pictet-Premium Brands R EUR",
                "PPMCode": "923383",
                "URL": "https://www.avanza.se/fonder/om-fonden.html/20949",
                "Current": 4.714070620111997,
                "Yesterday": 4.375515443311997,
                "LastWeek": 3.8897472675899913,
                "TrendDay": "\u25b2",
                "TrendWeek": "\u25b2",
                "TrendAwesome": "\ud83d\udcaa",
                "Label": "WEEKLYS",
                "LastUpdated": "2026-06-09 21:28:20 (UTC)",
                "history": false
            },
            {
                "Name": "DNB Health Care S",
                "PPMCode": "255001",
                "URL": "https://www.avanza.se/fonder/om-fonden.html/1506920",
                "Current": 5.685540975868007,
                "Yesterday": 6.259040091866991,
                "LastWeek": 3.2298192080740042,
                "TrendDay": "\u25bc",
                "TrendWeek": "\u25b2",
                "TrendAwesome": "",
                "Label": "WEEKLYS",
                "LastUpdated": "2026-06-09 21:28:26 (UTC)",
                "history": false
            }
        ]
    }
]