[
    {
        "Name": "BlackRock World Gold",
        "isin": "LU0055631609",
        "URL": "https://www.skandia.se/spara-pension/satt-att-spara/spara-fonder/fondlista#/fund/details/LU0055631609/USD",
        "LastUpdated": "2024-08-21 14:10:16 (UTC)",
        "Day": 1.72,
        "Week": 4.21
    },
    {
        "Name": "JPM Global Healthcare",
        "isin": "LU0432979614",
        "URL": "https://www.skandia.se/spara-pension/satt-att-spara/spara-fonder/fondlista#/fund/details/LU0432979614/USD",
        "LastUpdated": "2024-08-21 14:10:16 (UTC)",
        "Day": 0.35,
        "Week": 0.29
    },
    {
        "Name": "Norron Sustainable Preserve",
        "isin": "LU0580530409",
        "URL": "https://www.skandia.se/spara-pension/satt-att-spara/spara-fonder/fondlista#/fund/details/LU0580530409/SEK",
        "LastUpdated": "2024-08-21 14:10:16 (UTC)",
        "Day": 0.08,
        "Week": 0.11
    },
    {
        "Name": "Carnegie Corporate Bond",
        "isin": "LU0075898915",
        "URL": "https://www.skandia.se/spara-pension/satt-att-spara/spara-fonder/fondlista#/fund/details/LU0075898915/SEK",
        "LastUpdated": "2024-08-21 14:10:16 (UTC)",
        "Day": 0.05,
        "Week": 0.33
    },
    {
        "Name": "\u00d6hman FRN (SEKH)",
        "isin": "SE0004951283",
        "URL": "https://www.skandia.se/spara-pension/satt-att-spara/spara-fonder/fondlista#/fund/details/SE0004951283/SEK",
        "LastUpdated": "2024-08-21 14:10:16 (UTC)",
        "Day": 0.02,
        "Week": 0.14
    },
    {
        "Name": "Carnegie Likviditet",
        "isin": "SE0000429854",
        "URL": "https://www.skandia.se/spara-pension/satt-att-spara/spara-fonder/fondlista#/fund/details/SE0000429854/SEK",
        "LastUpdated": "2024-08-21 14:10:16 (UTC)",
        "Day": 0.01,
        "Week": 0.08
    },
    {
        "Name": "Skandia Kortr\u00e4nta",
        "isin": "SE0000810897",
        "URL": "https://www.skandia.se/spara-pension/satt-att-spara/spara-fonder/fondlista#/fund/details/SE0000810897/SEK",
        "LastUpdated": "2024-08-21 14:10:16 (UTC)",
        "Day": 0.01,
        "Week": 0.06
    }
]